.travis.yml
CHANGES.txt
MANIFEST.in
README.txt
__init__.py
bootstrap.py
build_test.sh
buildout.cfg
setup.cfg
setup.py
zopyx/__init__.py
zopyx.txng3.ext.egg-info/PKG-INFO
zopyx.txng3.ext.egg-info/SOURCES.txt
zopyx.txng3.ext.egg-info/dependency_links.txt
zopyx.txng3.ext.egg-info/namespace_packages.txt
zopyx.txng3.ext.egg-info/not-zip-safe
zopyx.txng3.ext.egg-info/requires.txt
zopyx.txng3.ext.egg-info/top_level.txt
zopyx/txng3/__init__.py
zopyx/txng3/ext/__init__.py
zopyx/txng3/ext/levenshtein.cpython-35m-x86_64-linux-gnu.so
zopyx/txng3/ext/levenshtein.so
zopyx/txng3/ext/normalizer.cpython-35m-x86_64-linux-gnu.so
zopyx/txng3/ext/normalizer.so
zopyx/txng3/ext/splitter.cpython-35m-x86_64-linux-gnu.so
zopyx/txng3/ext/splitter.so
zopyx/txng3/ext/stemmer.cpython-35m-x86_64-linux-gnu.so
zopyx/txng3/ext/stemmer.so
zopyx/txng3/ext/support.c
zopyx/txng3/ext/support.cpython-35m-x86_64-linux-gnu.so
zopyx/txng3/ext/support.so
zopyx/txng3/ext/normalizer_src/__init__.py
zopyx/txng3/ext/normalizer_src/normalizer.c
zopyx/txng3/ext/normalizer_src/tests/__init__.py
zopyx/txng3/ext/normalizer_src/tests/testNormalizer.py
zopyx/txng3/ext/python-Levenshtein-0.10/COPYING
zopyx/txng3/ext/python-Levenshtein-0.10/Levenshtein.c
zopyx/txng3/ext/python-Levenshtein-0.10/Levenshtein.h
zopyx/txng3/ext/python-Levenshtein-0.10/MANIFEST
zopyx/txng3/ext/python-Levenshtein-0.10/NEWS
zopyx/txng3/ext/python-Levenshtein-0.10/PKG-INFO
zopyx/txng3/ext/python-Levenshtein-0.10/README
zopyx/txng3/ext/python-Levenshtein-0.10/StringMatcher.py
zopyx/txng3/ext/python-Levenshtein-0.10/gendoc.sh
zopyx/txng3/ext/python-Levenshtein-0.10/setup.cfg
zopyx/txng3/ext/python-Levenshtein-0.10/setup.py
zopyx/txng3/ext/splitter_src/LICENSE
zopyx/txng3/ext/splitter_src/__init__.py
zopyx/txng3/ext/splitter_src/dict.c
zopyx/txng3/ext/splitter_src/dict.h
zopyx/txng3/ext/splitter_src/dict_private.h
zopyx/txng3/ext/splitter_src/hashtable.c
zopyx/txng3/ext/splitter_src/hashtable.h
zopyx/txng3/ext/splitter_src/splitter.c
zopyx/txng3/ext/splitter_src/tests/__init__.py
zopyx/txng3/ext/splitter_src/tests/testTXNGSplitter.py
zopyx/txng3/ext/stemmer/tests/out
zopyx/txng3/ext/stemmer_src/__init__.py
zopyx/txng3/ext/stemmer_src/stemmer.c
zopyx/txng3/ext/stemmer_src/libstemmer_c/MANIFEST
