Metadata-Version: 1.1
Name: zopyx.txng3.ext
Version: 3.5.0
Summary: Helper modules for TextIndexNG3 (Snowball stemmer, normalizer, splitter, etc.)
Home-page: http://sf.net/projects/textindexng/
Author: Andreas Jung, ZOPYX Ltd. & Co. KG
Author-email: info@zopyx.com
License: UNKNOWN
Platform: UNKNOWN
Classifier: Intended Audience :: Developers
Classifier: Programming Language :: Python
Classifier: Programming Language :: Python :: 2
Classifier: Programming Language :: Python :: 2.7
Classifier: Programming Language :: Python :: 3
Classifier: Programming Language :: Python :: 3.5
Classifier: Programming Language :: Python :: 3.6
Classifier: Programming Language :: Python :: Implementation :: CPython
Classifier: Programming Language :: Python :: Implementation :: PyPy
Classifier: Operating System :: OS Independent
